[{"inputs":[{"internalType":"address","name":"_owner","type":"address"},{"internalType":"address","name":"_house","type":"address"}],"stateMutability":"payable","type":"constructor"},{"inputs":[],"name":"BombGame__AlreadyClaimed","type":"error"},{"inputs":[],"name":"BombGame__AlreadyPlaying","type":"error"},{"inputs":[],"name":"BombGame__InsufficientBalance","type":"error"},{"inputs":[{"internalType":"uint256","name":"entryFee","type":"uint256"}],"name":"BombGame__InvalidEntryFee","type":"error"},{"inputs":[],"name":"BombGame__NoHouseTake","type":"error"},{"inputs":[],"name":"BombGame__NoWinnings","type":"error"},{"inputs":[],"name":"BombGame__OnlyHouse","type":"error"},{"inputs":[],"name":"BombGame__PlayerNotActive","type":"error"},{"inputs":[],"name":"BombGame__TransferFailed","type":"error"},{"inputs":[{"internalType":"address","name":"owner","type":"address"}],"name":"OwnableInvalidOwner","type":"error"},{"inputs":[{"internalType":"address","name":"account","type":"address"}],"name":"OwnableUnauthorizedAccount","type":"error"},{"anonymous":false,"inputs":[{"indexed":true,"internalType":"address","name":"player","type":"address"}],"name":"Entered","type":"event"},{"anonymous":false,"inputs":[{"indexed":true,"internalType":"address","name":"recipient","type":"address"},{"indexed":false,"internalType":"uint256","name":"amount","type":"uint256"}],"name":"HouseTakeWithdrawn","type":"event"},{"anonymous":false,"inputs":[{"indexed":true,"internalType":"address","name":"player","type":"address"}],"name":"Lose","type":"event"},{"anonymous":false,"inputs":[{"indexed":true,"internalType":"address","name":"previousOwner","type":"address"},{"indexed":true,"internalType":"address","name":"newOwner","type":"address"}],"name":"OwnershipTransferred","type":"event"},{"anonymous":false,"inputs":[{"indexed":false,"internalType":"uint256","name":"amount","type":"uint256"}],"name":"PoolFunded","type":"event"},{"anonymous":false,"inputs":[{"indexed":true,"internalType":"address","name":"winner","type":"address"},{"indexed":true,"internalType":"uint256","name":"amount","type":"uint256"},{"indexed":true,"internalType":"uint256","name":"nonce","type":"uint256"}],"name":"Win","type":"event"},{"anonymous":false,"inputs":[{"indexed":true,"internalType":"address","name":"winner","type":"address"},{"indexed":true,"internalType":"uint256","name":"amount","type":"uint256"},{"indexed":true,"internalType":"uint256","name":"nonce","type":"uint256"}],"name":"WinningsClaimed","type":"event"},{"inputs":[],"name":"ENTRY_FEE","outputs":[{"internalType":"uint256","name":"","type":"uint256"}],"stateMutability":"view","type":"function"},{"inputs":[],"name":"HOUSE_CUT","outputs":[{"internalType":"uint256","name":"","type":"uint256"}],"stateMutability":"view","type":"function"},{"inputs":[],"name":"PRECISION","outputs":[{"internalType":"uint256","name":"","type":"uint256"}],"stateMutability":"view","type":"function"},{"inputs":[],"name":"WIN_PERCENTAGE","outputs":[{"internalType":"uint256","name":"","type":"uint256"}],"stateMutability":"view","type":"function"},{"inputs":[{"internalType":"uint256","name":"_gameNonce","type":"uint256"}],"name":"claimWinnings","outputs":[],"stateMutability":"nonpayable","type":"function"},{"inputs":[{"internalType":"address","name":"_player","type":"address"},{"internalType":"bool","name":"_isWinner","type":"bool"}],"name":"endGame","outputs":[],"stateMutability":"nonpayable","type":"function"},{"inputs":[],"name":"fundPool","outputs":[],"stateMutability":"payable","type":"function"},{"inputs":[],"name":"gameNonce","outputs":[{"internalType":"uint256","name":"","type":"uint256"}],"stateMutability":"view","type":"function"},{"inputs":[{"internalType":"uint256","name":"","type":"uint256"}],"name":"hasClaimed","outputs":[{"internalType":"bool","name":"","type":"bool"}],"stateMutability":"view","type":"function"},{"inputs":[],"name":"house","outputs":[{"internalType":"address","name":"","type":"address"}],"stateMutability":"view","type":"function"},{"inputs":[],"name":"houseTake","outputs":[{"internalType":"uint256","name":"","type":"uint256"}],"stateMutability":"view","type":"function"},{"inputs":[{"internalType":"address","name":"","type":"address"}],"name":"isPlaying","outputs":[{"internalType":"bool","name":"","type":"bool"}],"stateMutability":"view","type":"function"},{"inputs":[],"name":"owner","outputs":[{"internalType":"address","name":"","type":"address"}],"stateMutability":"view","type":"function"},{"inputs":[],"name":"play","outputs":[],"stateMutability":"payable","type":"function"},{"inputs":[{"internalType":"uint256","name":"","type":"uint256"},{"internalType":"address","name":"","type":"address"}],"name":"playerWinnings","outputs":[{"internalType":"uint256","name":"","type":"uint256"}],"stateMutability":"view","type":"function"},{"inputs":[],"name":"prizePool","outputs":[{"internalType":"uint256","name":"","type":"uint256"}],"stateMutability":"view","type":"function"},{"inputs":[],"name":"renounceOwnership","outputs":[],"stateMutability":"nonpayable","type":"function"},{"inputs":[{"internalType":"address","name":"newOwner","type":"address"}],"name":"transferOwnership","outputs":[],"stateMutability":"nonpayable","type":"function"},{"inputs":[{"internalType":"address","name":"_recipient","type":"address"}],"name":"withdrawHouseTake","outputs":[],"stateMutability":"nonpayable","type":"function"}]